{"output":[{"explanation":"","index":0,"annotation":0,"possible_repair":""},{"explanation":"Misspelled compared with the dominant form \"surgical infection prevention\"; all three words contain anomalous x substitutions.","index":10,"annotation":1,"possible_repair":"surgical infection prevention"},{"explanation":"Misspelled compared with the dominant form \"surgical infection prevention\"; all three words contain x-substituted letters.","index":11,"annotation":1,"possible_repair":"surgical infection prevention"},{"explanation":"Misspelled compared with the dominant form \"surgical infection prevention\"; \"xrevention\" deviates from \"prevention\".","index":24,"annotation":1,"possible_repair":"surgical infection prevention"},{"explanation":"Misspelled compared with the dominant form \"surgical infection prevention\"; \"infxction\" and \"prxvxntion\" deviate from the common spelling.","index":26,"annotation":1,"possible_repair":"surgical infection prevention"},{"explanation":"Misspelled compared with the dominant form \"surgical infection prevention\"; \"xnfection\" deviates from \"infection\".","index":27,"annotation":1,"possible_repair":"surgical infection prevention"},{"explanation":"","index":1,"annotation":0,"possible_repair":""},{"explanation":"Misspelled compared with the dominant form \"heart attack\"; \"attaxk\" deviates from \"attack\".","index":3,"annotation":1,"possible_repair":"heart attack"},{"explanation":"Pattern non-conformity: the common form is two words like \"heart attack\", but this value merges them and also uses an x-substituted letter.","index":25,"annotation":1,"possible_repair":"heart attack"},{"explanation":"Misspelled compared with the dominant form \"heart failure\"; \"faxlure\" deviates from \"failure\".","index":9,"annotation":1,"possible_repair":"heart failure"},{"explanation":"","index":2,"annotation":0,"possible_repair":""},{"explanation":"Misspelled compared with the dominant form \"heart failure\"; \"faixure\" deviates from \"failure\".","index":20,"annotation":1,"possible_repair":"heart failure"},{"explanation":"Misspelled compared with the dominant form \"heart failure\"; \"xeart\" deviates from \"heart\".","index":13,"annotation":1,"possible_repair":"heart failure"},{"explanation":"Misspelled compared with the dominant form \"heart attack\"; both words deviate as \"hearx axxack\".","index":4,"annotation":1,"possible_repair":"heart attack"},{"explanation":"","index":5,"annotation":0,"possible_repair":""},{"explanation":"Misspelled compared with the dominant form \"pneumonia\"; initial letter differs as \"xneumonia\".","index":12,"annotation":1,"possible_repair":"pneumonia"},{"explanation":"Misspelled compared with the dominant form \"pneumonia\"; \"pnexmonia\" deviates by x substitution.","index":16,"annotation":1,"possible_repair":"pneumonia"},{"explanation":"Misspelled compared with the dominant form \"pneumonia\"; final letters differ as \"pneumonix\".","index":18,"annotation":1,"possible_repair":"pneumonia"},{"explanation":"Misspelled compared with the dominant form \"pneumonia\"; final letters differ as \"pneumonxa\".","index":22,"annotation":1,"possible_repair":"pneumonia"},{"explanation":"Misspelled compared with the dominant form \"heart failure\"; both words deviate as \"heaxt failuxe\".","index":6,"annotation":1,"possible_repair":"heart failure"},{"explanation":"Misspelled compared with the dominant form \"heart attack\"; \"heaxt\" deviates from \"heart\".","index":7,"annotation":1,"possible_repair":"heart attack"},{"explanation":"Misspelled compared with the dominant form \"heart attack\"; both words deviate as \"hexrt attxck\".","index":8,"annotation":1,"possible_repair":"heart attack"},{"explanation":"","index":14,"annotation":0,"possible_repair":""},{"explanation":"Misspelled compared with the dominant form \"xneumonia\" appears as duplicate index in input, but against the dominant valid form \"pneumonia\" it deviates in the first letter.","index":12,"annotation":1,"possible_repair":"pneumonia"},{"explanation":"Misspelled compared with the dominant form \"pneumonia\"; \"pnxumonia\" deviates by x substitution.","index":15,"annotation":1,"possible_repair":"pneumonia"},{"explanation":"Misspelled compared with the dominant form \"heart failure\"; both words deviate as \"hxart failurx\".","index":17,"annotation":1,"possible_repair":"heart failure"},{"explanation":"Misspelled compared with the dominant form \"heart failure\"; \"xeart\" deviates from \"heart\".","index":13,"annotation":1,"possible_repair":"heart failure"},{"explanation":"Misspelled compared with the dominant form \"pneumonia\"; multiple letters differ in \"pxeumoxia\".","index":19,"annotation":1,"possible_repair":"pneumonia"},{"explanation":"Misspelled compared with the dominant form \"surgical infection prevention\"; all three words deviate with x-substituted letters.","index":21,"annotation":1,"possible_repair":"surgical infection prevention"},{"explanation":"Misspelled compared with the dominant form \"heart failure\"; both words deviate as \"hexrt fxilure\".","index":23,"annotation":1,"possible_repair":"heart failure"}]}