{"output":[{"explanation":"","index":0,"annotation":0,"possible_repair":""},{"explanation":"Contains 'x' which is an invalid character compared to the correct pattern found in 'birmingham'.","index":1,"annotation":1,"possible_repair":"birmingham"},{"explanation":"Contains 'x' which is an invalid character compared to the correct pattern found in 'birmingham'.","index":2,"annotation":1,"possible_repair":"birmingham"},{"explanation":"","index":3,"annotation":0,"possible_repair":""},{"explanation":"Contains 'x' which is an invalid character compared to the correct pattern found in 'sheffield'.","index":4,"annotation":1,"possible_repair":"sheffield"},{"explanation":"","index":5,"annotation":0,"possible_repair":""},{"explanation":"","index":6,"annotation":0,"possible_repair":""},{"explanation":"'boxz' contains 'z' which is an invalid character compared to others.","index":7,"annotation":1,"possible_repair":"box"},{"explanation":"","index":8,"annotation":0,"possible_repair":""},{"explanation":"Contains 'x' which is an invalid character compared to the correct pattern found in 'florence'.","index":9,"annotation":1,"possible_repair":"florence"},{"explanation":"Contains 'x' which is an invalid character compared to the correct pattern found in 'florence'.","index":10,"annotation":1,"possible_repair":"florence"},{"explanation":"Contains 'x' which is an invalid character compared to the correct pattern found in 'florence'.","index":11,"annotation":1,"possible_repair":"florence"},{"explanation":"","index":12,"annotation":0,"possible_repair":""},{"explanation":"","index":13,"annotation":0,"possible_repair":""},{"explanation":"Contains 'x' which is an invalid character compared to the correct pattern found in 'guntersville'.","index":16,"annotation":1,"possible_repair":"guntersville"},{"explanation":"Contains 'x' which is an invalid character compared to the correct pattern found in 'birmingham'.","index":17,"annotation":1,"possible_repair":"birmingham"},{"explanation":"Contains 'x' which is an invalid character compared to the correct pattern found in 'birmingham'.","index":18,"annotation":1,"possible_repair":"birmingham"},{"explanation":"","index":19,"annotation":0,"possible_repair":""},{"explanation":"Contains 'x' which is an invalid character compared to the correct pattern found in 'fort payne'.","index":20,"annotation":1,"possible_repair":"fort payne"},{"explanation":"","index":21,"annotation":0,"possible_repair":""},{"explanation":"","index":22,"annotation":0,"possible_repair":""},{"explanation":"'axxistox' has 'x' which deviates from 'andalusia'.","index":23,"annotation":1,"possible_repair":"andalusia"},{"explanation":"","index":24,"annotation":0,"possible_repair":""},{"explanation":"","index":25,"annotation":0,"possible_repair":""},{"explanation":"","index":26,"annotation":0,"possible_repair":""},{"explanation":"Contains 'x' which is an invalid character compared to the correct pattern found in 'winfield'.","index":27,"annotation":1,"possible_repair":"winfield"},{"explanation":"","index":28,"annotation":0,"possible_repair":""},{"explanation":"","index":29,"annotation":0,"possible_repair":""},{"explanation":"","index":30,"annotation":0,"possible_repair":""},{"explanation":"","index":31,"annotation":0,"possible_repair":""},{"explanation":"","index":32,"annotation":0,"possible_repair":""},{"explanation":"Contains 'x' which is an invalid character compared to the correct pattern found in 'anchorage'.","index":33,"annotation":1,"possible_repair":"anchorage"},{"explanation":"","index":34,"annotation":0,"possible_repair":""},{"explanation":"","index":35,"annotation":0,"possible_repair":""},{"explanation":"Contains 'x' which is an invalid character compared to the correct pattern found in 'ozark'.","index":36,"annotation":1,"possible_repair":"ozark"},{"explanation":"Contains 'x' which is an invalid character compared to the correct pattern found in 'ozark'.","index":37,"annotation":1,"possible_repair":"ozark"},{"explanation":"","index":38,"annotation":0,"possible_repair":""},{"explanation":"","index":39,"annotation":0,"possible_repair":""},{"explanation":"Contains 'x' which is an invalid character compared to the correct pattern found in 'valley'.","index":42,"annotation":1,"possible_repair":"valley"},{"explanation":"Contains 'x' which is an invalid character compared to the correct pattern found in 'valley'.","index":43,"annotation":1,"possible_repair":"valley"},{"explanation":"","index":44,"annotation":0,"possible_repair":""},{"explanation":"Contains 'x' which is an invalid character compared to the correct pattern found in 'elba'.","index":45,"annotation":1,"possible_repair":"elba"},{"explanation":"","index":46,"annotation":0,"possible_repair":""},{"explanation":"","index":47,"annotation":0,"possible_repair":""},{"explanation":"Contains 'x' which is an invalid character compared to the correct pattern found in 'wedowee'.","index":48,"annotation":1,"possible_repair":"wedowee"},{"explanation":"Contains 'x' which is an invalid character compared to the correct pattern found in 'birminxham'.","index":49,"annotation":1,"possible_repair":"birmingham"},{"explanation":"","index":50,"annotation":0,"possible_repair":""},{"explanation":"Contains 'x' which is an invalid character compared to the correct pattern found in 'tallassee'.","index":51,"annotation":1,"possible_repair":"tallassee"},{"explanation":"","index":52,"annotation":0,"possible_repair":""},{"explanation":"Contains 'x' which is an invalid character compared to the correct pattern found in 'cullman'.","index":53,"annotation":1,"possible_repair":"cullman"},{"explanation":"","index":54,"annotation":0,"possible_repair":""},{"explanation":"Contains 'x' which is an invalid character compared to the correct pattern found in 'andalusia'.","index":55,"annotation":1,"possible_repair":"andalusia"},{"explanation":"Contains 'x' which is an invalid character compared to the correct pattern found in 'anniston'.","index":56,"annotation":1,"possible_repair":"anniston"},{"explanation":"","index":57,"annotation":0,"possible_repair":""},{"explanation":"","index":58,"annotation":0,"possible_repair":""},{"explanation":"Contains 'x' which is an invalid character compared to the correct pattern found in 'gadsden'.","index":59,"annotation":1,"possible_repair":"gadsden"},{"explanation":"","index":60,"annotation":0,"possible_repair":""},{"explanation":"Contains 'x' which is an invalid character compared to the correct pattern found in 'hamilton'.","index":62,"annotation":1,"possible_repair":"hamilton"},{"explanation":"","index":63,"annotation":0,"possible_repair":""},{"explanation":"Contains 'x' which is an invalid character compared to the correct pattern found in 'georgiana'.","index":66,"annotation":1,"possible_repair":"georgiana"},{"explanation":"","index":67,"annotation":0,"possible_repair":""},{"explanation":"Contains 'x' which is an invalid character compared to the correct pattern found in 'enterprise'.","index":68,"annotation":1,"possible_repair":"enterprise"},{"explanation":"Contains 'x' which is an invalid character compared to the correct pattern found in 'enterprise'.","index":69,"annotation":1,"possible_repair":"enterprise"},{"explanation":"","index":70,"annotation":0,"possible_repair":""},{"explanation":"Contains 'x' which is an invalid character compared to the correct pattern found in 'oneonta'.","index":71,"annotation":1,"possible_repair":"oneonta"}]}