{"output":[{"explanation":"","index":0,"annotation":0,"possible_repair":"2053258100"},{"explanation":"","index":1,"annotation":0,"possible_repair":"2563864556"},{"explanation":"","index":2,"annotation":0,"possible_repair":"3347938701"},{"explanation":"Contains non-digit character 'x', while the column values are otherwise 10-digit numeric strings.","index":3,"annotation":1,"possible_repair":"3347938701"},{"explanation":"Contains letters and uses a masked pattern unlike the fully numeric values that dominate the column.","index":25,"annotation":1,"possible_repair":"3347935000"},{"explanation":"Contains letters and a masked pattern; other values are 10-digit numeric strings.","index":4,"annotation":1,"possible_repair":"3347938701"},{"explanation":"","index":5,"annotation":0,"possible_repair":"2565938310"},{"explanation":"Contains an internal 'x' instead of a digit, unlike the numeric pattern seen in the column.","index":7,"annotation":1,"possible_repair":"2565938310"},{"explanation":"Contains multiple 'x' placeholders; other values are 10-digit numeric strings.","index":6,"annotation":1,"possible_repair":"2565938310"},{"explanation":"","index":8,"annotation":0,"possible_repair":"2567688400"},{"explanation":"","index":9,"annotation":0,"possible_repair":"3344933541"},{"explanation":"Contains a non-digit 'x'; the rest of the column values are numeric strings.","index":10,"annotation":1,"possible_repair":"3344933541"},{"explanation":"","index":11,"annotation":0,"possible_repair":"3343353374"},{"explanation":"","index":12,"annotation":0,"possible_repair":"2567736511"},{"explanation":"","index":13,"annotation":0,"possible_repair":"2565718000"},{"explanation":"","index":14,"annotation":0,"possible_repair":"2058383122"},{"explanation":"Contains 'x' placeholders instead of digits, unlike the standard numeric format.","index":15,"annotation":1,"possible_repair":"2058383122"},{"explanation":"","index":16,"annotation":0,"possible_repair":"2568453150"},{"explanation":"Contains an 'x' within an otherwise numeric string; other values are digits only.","index":17,"annotation":1,"possible_repair":"2568453150"},{"explanation":"","index":18,"annotation":0,"possible_repair":"3346366221"},{"explanation":"Contains masked characters 'x' instead of digits; not consistent with the column's numeric strings.","index":19,"annotation":1,"possible_repair":"3346366221"},{"explanation":"Contains multiple 'x' placeholders, unlike the fully numeric values in the list.","index":20,"annotation":1,"possible_repair":"3346366221"},{"explanation":"","index":21,"annotation":0,"possible_repair":"2056208100"},{"explanation":"","index":22,"annotation":0,"possible_repair":"2562358900"},{"explanation":"Contains an 'x' character; the dominant pattern is a 10-digit number.","index":23,"annotation":1,"possible_repair":"2562358900"},{"explanation":"","index":24,"annotation":0,"possible_repair":"3347935000"},{"explanation":"","index":26,"annotation":0,"possible_repair":"2059397000"},{"explanation":"","index":27,"annotation":0,"possible_repair":"2563412000"},{"explanation":"","index":28,"annotation":0,"possible_repair":"2054877736"},{"explanation":"","index":29,"annotation":0,"possible_repair":"2514717110"},{"explanation":"Contains multiple 'x' placeholders and does not fully conform to the numeric-only pattern.","index":30,"annotation":1,"possible_repair":"2547770000"},{"explanation":"","index":31,"annotation":0,"possible_repair":"3343614267"},{"explanation":"Contains an 'x' placeholder; other values are numeric strings of the same length.","index":32,"annotation":1,"possible_repair":"3343614267"},{"explanation":"","index":33,"annotation":0,"possible_repair":"2563321611"},{"explanation":"","index":34,"annotation":0,"possible_repair":"2562495000"},{"explanation":"","index":35,"annotation":0,"possible_repair":"9072761131"},{"explanation":"","index":36,"annotation":0,"possible_repair":"9075436300"},{"explanation":"","index":37,"annotation":0,"possible_repair":"3347742601"},{"explanation":"Contains an 'x' in place of a digit; the column otherwise uses numeric strings.","index":38,"annotation":1,"possible_repair":"3347742601"},{"explanation":"","index":39,"annotation":0,"possible_repair":"2569275531"},{"explanation":"Contains 'x' placeholders; does not match the prevalent all-digit structure.","index":40,"annotation":1,"possible_repair":"3342882100"},{"explanation":"","index":41,"annotation":0,"possible_repair":"3342882100"},{"explanation":"","index":42,"annotation":0,"possible_repair":"3342938000"},{"explanation":"Contains trailing 'x' placeholders instead of digits, unlike the other values.","index":43,"annotation":1,"possible_repair":"3342938000"},{"explanation":"Contains an 'x' in a digit position; the rest of the list is numeric.","index":44,"annotation":1,"possible_repair":"3342938000"},{"explanation":"","index":45,"annotation":0,"possible_repair":"3347561400"},{"explanation":"Contains an 'x' placeholder; other entries are 10-digit numbers.","index":46,"annotation":1,"possible_repair":"3347561400"},{"explanation":"","index":48,"annotation":0,"possible_repair":"3348972257"},{"explanation":"","index":47,"annotation":0,"possible_repair":"3348972257"},{"explanation":"","index":49,"annotation":0,"possible_repair":"3347493411"},{"explanation":"","index":50,"annotation":0,"possible_repair":"2563572111"},{"explanation":"Contains 'xx' placeholders in the middle, unlike the numeric-only column values.","index":51,"annotation":1,"possible_repair":"2059344011"},{"explanation":"","index":52,"annotation":0,"possible_repair":"2059344011"},{"explanation":"","index":53,"annotation":0,"possible_repair":"3342836541"},{"explanation":"Contains an 'x' placeholder instead of a digit; other values are all digits.","index":54,"annotation":1,"possible_repair":"3342836541"},{"explanation":"Contains multiple 'x' placeholders; deviates from the 10-digit numeric pattern.","index":55,"annotation":1,"possible_repair":"3342836541"},{"explanation":"","index":56,"annotation":0,"possible_repair":"2567372000"},{"explanation":"","index":57,"annotation":0,"possible_repair":"3342228466"},{"explanation":"Contains masked characters 'x' at the end, unlike the fully numeric values.","index":59,"annotation":1,"possible_repair":"3342228466"},{"explanation":"Contains masked characters 'x' in place of digits; column values are numeric strings.","index":58,"annotation":1,"possible_repair":"3342228466"},{"explanation":"","index":60,"annotation":0,"possible_repair":"2562651000"},{"explanation":"","index":61,"annotation":0,"possible_repair":"2564944000"},{"explanation":"Contains trailing 'x' placeholders instead of digits, unlike the predominant pattern.","index":62,"annotation":1,"possible_repair":"2564944000"},{"explanation":"","index":63,"annotation":0,"possible_repair":"2057552500"},{"explanation":"","index":64,"annotation":0,"possible_repair":"2059216200"},{"explanation":"Contains 'x' placeholders and does not conform to the all-digit format.","index":65,"annotation":1,"possible_repair":"2059216200"},{"explanation":"Contains an 'x' character, whereas the rest of the column values are numeric.","index":66,"annotation":1,"possible_repair":"2059216200"},{"explanation":"","index":67,"annotation":0,"possible_repair":"2059325966"},{"explanation":"Contains 'x' placeholders instead of digits; this breaks the numeric pattern.","index":68,"annotation":1,"possible_repair":"2059325966"},{"explanation":"","index":69,"annotation":0,"possible_repair":"2565435200"},{"explanation":"Contains 'x' placeholders; other values in the column are 10-digit numbers.","index":70,"annotation":1,"possible_repair":"2565435200"},{"explanation":"","index":71,"annotation":0,"possible_repair":"3343762205"},{"explanation":"","index":72,"annotation":0,"possible_repair":"3343470584"},{"explanation":"","index":73,"annotation":0,"possible_repair":"2052743000"}]}