{"output":[{"explanation":"Contains only lowercase letters and matches the dominant short text/brand-like pattern seen in the column.","index":0,"annotation":0,"possible_repair":""},{"explanation":"Contains only lowercase letters and fits the common single-token brand/name pattern.","index":1,"annotation":0,"possible_repair":""},{"explanation":"Contains only lowercase letters and matches many other values with the same simple token structure.","index":13,"annotation":0,"possible_repair":""},{"explanation":"Contains only lowercase letters and matches the common location-like token pattern in the column.","index":2,"annotation":0,"possible_repair":""},{"explanation":"Contains only lowercase letters and fits the prevalent one-word token pattern.","index":3,"annotation":0,"possible_repair":""},{"explanation":"Contains only lowercase letters and matches the prevalent concatenated-word pattern.","index":4,"annotation":0,"possible_repair":""},{"explanation":"Contains only lowercase letters and matches the prevalent concatenated-word pattern.","index":5,"annotation":0,"possible_repair":""},{"explanation":"Contains only lowercase letters and matches many other values with the same simple token structure.","index":13,"annotation":0,"possible_repair":""},{"explanation":"Contains only lowercase letters and fits the prevalent concatenated-word pattern.","index":6,"annotation":0,"possible_repair":""},{"explanation":"Contains only lowercase letters and matches the prevalent short abbreviation pattern.","index":7,"annotation":0,"possible_repair":""},{"explanation":"Contains only lowercase letters and matches the prevalent concatenated-word pattern.","index":8,"annotation":0,"possible_repair":""},{"explanation":"Contains only lowercase letters and matches the prevalent short code pattern.","index":9,"annotation":0,"possible_repair":""},{"explanation":"Contains only lowercase letters and matches the prevalent short code pattern.","index":10,"annotation":0,"possible_repair":""},{"explanation":"Contains only lowercase letters and matches the prevalent short code pattern.","index":11,"annotation":0,"possible_repair":""},{"explanation":"Contains only lowercase letters and matches the prevalent short code pattern.","index":12,"annotation":0,"possible_repair":""},{"explanation":"Contains only lowercase letters and matches the prevalent concatenated-word pattern.","index":14,"annotation":0,"possible_repair":""},{"explanation":"Contains only lowercase letters and matches many other values with the same simple token structure.","index":13,"annotation":0,"possible_repair":""},{"explanation":"Contains only lowercase letters and matches the prevalent concatenated-word pattern.","index":15,"annotation":0,"possible_repair":""},{"explanation":"Contains only lowercase letters and matches the prevalent concatenated-word pattern.","index":16,"annotation":0,"possible_repair":""},{"explanation":"Contains only lowercase letters and matches the prevalent concatenated-word pattern.","index":17,"annotation":0,"possible_repair":""},{"explanation":"Contains only lowercase letters and matches the prevalent concatenated-word pattern.","index":18,"annotation":0,"possible_repair":""},{"explanation":"Contains only lowercase letters and matches the prevalent concatenated-word pattern.","index":19,"annotation":0,"possible_repair":""},{"explanation":"Contains only lowercase letters and matches the prevalent short token pattern.","index":20,"annotation":0,"possible_repair":""},{"explanation":"Contains only lowercase letters and matches the prevalent three-letter code pattern.","index":21,"annotation":0,"possible_repair":""},{"explanation":"Uses uppercase letters, unlike the overwhelmingly lowercase values in the column.","index":22,"annotation":1,"possible_repair":"co"},{"explanation":"Contains only lowercase letters and matches the prevalent short token pattern.","index":23,"annotation":0,"possible_repair":""},{"explanation":"Contains only lowercase letters and matches the prevalent three-letter code pattern.","index":24,"annotation":0,"possible_repair":""},{"explanation":"Contains only lowercase letters and matches the prevalent concatenated-word pattern.","index":25,"annotation":0,"possible_repair":""},{"explanation":"Contains only lowercase letters and matches the prevalent concatenated-word pattern.","index":26,"annotation":0,"possible_repair":""},{"explanation":"Contains only lowercase letters and matches the prevalent three-letter code pattern.","index":27,"annotation":0,"possible_repair":""},{"explanation":"Contains only lowercase letters and matches the prevalent concatenated-word pattern.","index":28,"annotation":0,"possible_repair":""},{"explanation":"Contains only lowercase letters and matches the prevalent short token pattern.","index":29,"annotation":0,"possible_repair":""},{"explanation":"Contains only lowercase letters and matches the prevalent concatenated-word pattern.","index":30,"annotation":0,"possible_repair":""},{"explanation":"Contains only lowercase letters and matches the prevalent concatenated-word pattern.","index":31,"annotation":0,"possible_repair":""},{"explanation":"Contains only lowercase letters and matches the prevalent concatenated-word pattern.","index":32,"annotation":0,"possible_repair":""},{"explanation":"Contains only lowercase letters and matches the prevalent concatenated-word pattern.","index":33,"annotation":0,"possible_repair":""},{"explanation":"Contains only lowercase letters and matches the prevalent three-letter code pattern.","index":34,"annotation":0,"possible_repair":""},{"explanation":"Contains only lowercase letters and matches the prevalent concatenated-word pattern.","index":35,"annotation":0,"possible_repair":""},{"explanation":"Contains only lowercase letters and matches the prevalent concatenated-word pattern.","index":36,"annotation":0,"possible_repair":""},{"explanation":"Contains hyphens, but most other values are single uninterrupted lowercase tokens.","index":37,"annotation":1,"possible_repair":"worldflighttracker"}]}